src/__init__.py
src/__main__.py
src/config.default.json
src/config.json
src/main_server.py
src/admin/__init__.py
src/admin/admin_server.py
src/config/__init__.py
src/config/config.py
src/confirmation/__init__.py
src/confirmation/confirmation.py
src/confirmation/confirmation_handlers.py
src/es_client/__init__.py
src/es_client/document_schema.py
src/es_client/elasticsearch_client.py
src/es_client/elasticsearch_helper.py
src/es_client/elasticsearch_server.py
src/es_client/elasticsearch_setup.py
src/es_client/sub_servers/__init__.py
src/es_client/sub_servers/elasticsearch_batch.py
src/es_client/sub_servers/elasticsearch_document.py
src/es_client/sub_servers/elasticsearch_index.py
src/es_client/sub_servers/elasticsearch_index_metadata.py
src/es_client/sub_servers/elasticsearch_search.py
src/es_client/sub_servers/elasticsearch_snapshots.py
src/middleware/__init__.py
src/middleware/confirmation_middleware.py
src/prompts/__init__.py
src/prompts/prompt_server.py
src/prompts/sub_servers/__init__.py
src/prompts/sub_servers/instructions_server.py
src/prompts/sub_servers/smart_prompting_server.py
src/prompts/templates/memories_assistant.md
src/prompts/templates/rules_assistant.md
src/prompts/templates/workflow_assistant.md
src/resources/copilot-instructions.md
src/utils/__init__.py
src/utils/security.py
iflow_mcp_itshare4u_agent_knowledge_mcp-2.2.1.dist-info/METADATA
iflow_mcp_itshare4u_agent_knowledge_mcp-2.2.1.dist-info/WHEEL
iflow_mcp_itshare4u_agent_knowledge_mcp-2.2.1.dist-info/entry_points.txt
iflow_mcp_itshare4u_agent_knowledge_mcp-2.2.1.dist-info/licenses/LICENSE
iflow_mcp_itshare4u_agent_knowledge_mcp-2.2.1.dist-info/RECORD
