Metadata-Version: 2.4
Name: iflow-mcp_itshare4u_agent-knowledge-mcp
Version: 2.2.1
Summary: AgentKnowledgeMCP - Advanced Knowledge Management for AI Agents
Project-URL: Homepage, https://github.com/itshare4u/AgentKnowledgeMCP
Project-URL: Repository, https://github.com/itshare4u/AgentKnowledgeMCP
Project-URL: Documentation, https://github.com/itshare4u/AgentKnowledgeMCP#readme
Project-URL: Issues, https://github.com/itshare4u/AgentKnowledgeMCP/issues
Project-URL: Funding, https://github.com/sponsors/itshare4u
Project-URL: Buy Me Coffee, https://coff.ee/itshare4u
Project-URL: Changelog, https://github.com/itshare4u/AgentKnowledgeMCP/blob/main/CHANGELOG.md
Author-email: Agent Knowledge MCP Contributors <contributors@agent-knowledge-mcp.dev>
License: MIT
License-File: LICENSE
Keywords: ai,automation,elasticsearch,knowledge-management,mcp
Classifier: Development Status :: 4 - Beta
Classifier: Intended Audience :: Developers
Classifier: License :: OSI Approved :: MIT License
Classifier: Programming Language :: Python :: 3
Classifier: Programming Language :: Python :: 3.10
Classifier: Programming Language :: Python :: 3.11
Classifier: Programming Language :: Python :: 3.12
Classifier: Programming Language :: Python :: 3.13
Classifier: Topic :: Scientific/Engineering :: Artificial Intelligence
Classifier: Topic :: Software Development :: Libraries :: Python Modules
Requires-Python: >=3.10
Requires-Dist: docker>=7.0.0
Requires-Dist: elasticsearch<8.0.0,>=7.0.0
Requires-Dist: fastmcp>=0.15.0
Requires-Dist: mcp>=1.10.1
Requires-Dist: pydantic>=2.0.0
Requires-Dist: requests>=2.32.0
Provides-Extra: dev
Requires-Dist: black>=23.0.0; extra == 'dev'
Requires-Dist: isort>=5.12.0; extra == 'dev'
Requires-Dist: mypy>=1.5.0; extra == 'dev'
Requires-Dist: pytest-asyncio>=0.21.0; extra == 'dev'
Requires-Dist: pytest>=7.0.0; extra == 'dev'
